oc_meta/__init__.py
oc_meta/constants.py
oc_meta/core/__init__.py
oc_meta/core/creator.py
oc_meta/core/curator.py
oc_meta/datasource/__init__.py
oc_meta/datasource/config.ini
oc_meta/datasource/datasource.py
oc_meta/datasource/redis.py
oc_meta/lib/__init__.py
oc_meta/lib/cleaner.py
oc_meta/lib/csvmanager.py
oc_meta/lib/file_manager.py
oc_meta/lib/finder.py
oc_meta/lib/jsonmanager.py
oc_meta/lib/master_of_regex.py
oc_meta/lib/reporter.py
oc_meta/lib/stopper.py
oc_meta/plugins/__init__.py
oc_meta/plugins/analyser.py
oc_meta/plugins/ar_order_check.py
oc_meta/plugins/check_meta_output.py
oc_meta/plugins/csv_generator/csv_generator.py
oc_meta/plugins/csv_generator_lite/csv_generator_lite.py
oc_meta/plugins/editor.py
oc_meta/plugins/fixer/ar_order.py
oc_meta/plugins/fixer/custom.py
oc_meta/plugins/fixer/merge_duplicated_ids.py
oc_meta/plugins/generate_table_from_list_of_ids.py
oc_meta/plugins/get_entities_count.py
oc_meta/plugins/get_ids_from_citations.py
oc_meta/plugins/language_count.py
oc_meta/plugins/multiprocess/prepare_multiprocess.py
oc_meta/plugins/multiprocess/resp_agents_creator.py
oc_meta/plugins/multiprocess/resp_agents_curator.py
oc_meta/plugins/orcid/__init__.py
oc_meta/plugins/orcid/index_orcid_doi.py
oc_meta/plugins/redis_key_counter.py
oc_meta/run/__init__.py
oc_meta/run/add_missing_ids.py
oc_meta/run/align_rdf_with_triplestore.py
oc_meta/run/analyser/count_authors_with_orcid.py
oc_meta/run/analyser/find_br_with_multiple_re.py
oc_meta/run/analyser/find_entities_without_prov.py
oc_meta/run/analyser/find_orphans.py
oc_meta/run/analyser/find_re_to_be_deleted.py
oc_meta/run/analyser/find_referenced_without_triples.py
oc_meta/run/analyser/meta_analyser.py
oc_meta/run/analyser/meta_rdf_analyser.py
oc_meta/run/analyser/se_without_source.py
oc_meta/run/analyser/validate_metadata.py
oc_meta/run/check/info_dir.py
oc_meta/run/check_provenance.py
oc_meta/run/count_triples_in_rdf.py
oc_meta/run/csv_generator.py
oc_meta/run/csv_generator_lite.py
oc_meta-2.1.3.dist-info/LICENSE.md
oc_meta-2.1.3.dist-info/METADATA
oc_meta-2.1.3.dist-info/WHEEL
oc_meta-2.1.3.dist-info/entry_points.txt
oc_meta-2.1.3.dist-info/RECORD
