Metadata-Version: 2.3
Name: oc_meta
Version: 2.1.3
Summary: OpenCitations Meta contains bibliographic metadata associated with the documents involved in the citations stored in the OpenCitations infrastructure. The OpenCitations Meta Software performs two main actions: a data curation of the provided CSV files and the generation of new RDF files compliant with the OpenCitations Data Model.
License: ISC
Author: Arcangelo Massari
Author-email: arcangelomas@gmail.com
Requires-Python: >=3.10,<3.14
Classifier: License :: OSI Approved
Classifier: Programming Language :: Python :: 3
Classifier: Programming Language :: Python :: 3.10
Classifier: Programming Language :: Python :: 3.11
Classifier: Programming Language :: Python :: 3.12
Classifier: Programming Language :: Python :: 3.13
Requires-Dist: Pebble (>=5.0.3,<6.0.0)
Requires-Dist: PyYAML (>=6.0,<7.0)
Requires-Dist: argparse (>=1.4.0,<2.0.0)
Requires-Dist: beautifulsoup4 (>=4.11.1,<5.0.0)
Requires-Dist: fakeredis (>=2.10.3,<3.0.0)
Requires-Dist: filelock (>=3.13,<4.0)
Requires-Dist: ijson (>=3.2.3,<4.0.0)
Requires-Dist: internetarchive (>=5.2.0,<6.0.0)
Requires-Dist: lxml (>=4.9.2,<6.0.0)
Requires-Dist: ndjson (>=0.3.1,<0.4.0)
Requires-Dist: numpy (>=2.1.1,<3.0.0)
Requires-Dist: oc-ds-converter (>=1.0.4,<2.0.0)
Requires-Dist: oc-ocdm (==9.2.1)
Requires-Dist: orjson (>=3.10.7,<4.0.0)
Requires-Dist: pandas (>=2.2.3,<3.0.0)
Requires-Dist: psutil (>=5.9.0,<6.0.0)
Requires-Dist: python-dateutil (>=2.8.2,<3.0.0)
Requires-Dist: rdflib (>=6.1.1,<7.0.0)
Requires-Dist: rdflib-ocdm (>=1.0.2,<2.0.0)
Requires-Dist: requests (>=2.27.1,<3.0.0)
Requires-Dist: retrying (>=1.3.4,<2.0.0)
Requires-Dist: sparqlwrapper (==2.0.0)
Requires-Dist: time-agnostic-library (>=4.7.1,<5.0.0)
Requires-Dist: tqdm (>=4.64.0,<5.0.0)
Requires-Dist: zenodopy (>=0.3.0,<0.4.0)
Requires-Dist: zstandard (>=0.21.0,<0.22.0)
